README.md
setup.py
whop/__init__.py
whop/whop.py
whop_sdk_py.egg-info/PKG-INFO
whop_sdk_py.egg-info/SOURCES.txt
whop_sdk_py.egg-info/dependency_links.txt
whop_sdk_py.egg-info/requires.txt
whop_sdk_py.egg-info/top_level.txt