Metadata-Version: 2.1
Name: whop-sdk-py
Version: 0.0.0
Summary: A package for to control Whop API for humans
Author: Noah Gomes
Author-email: noahgomes02@yahoo.com
Requires-Dist: requests
